clitellum/__init__.py
clitellum/atomic.py
clitellum/exceptions.py
clitellum/handlers.py
clitellum/logger_manager.py
clitellum/microservices.py
clitellum/services.py
clitellum/channels/__init__.py
clitellum/channels/amqp.py
clitellum/channels/channel.py
clitellum/channels/configuration.py
clitellum-5.2.4.dist-info/LICENSE
clitellum-5.2.4.dist-info/METADATA
clitellum-5.2.4.dist-info/WHEEL
clitellum-5.2.4.dist-info/top_level.txt
clitellum-5.2.4.dist-info/RECORD
