Metadata-Version: 2.1
Name: clitellum
Version: 5.2.4
Summary: Clitellum Microservice Framework
Home-page: https://clitellum.hotaka.io
Author: Sergio.Bermudez
Author-email: sergio@hotaka.io
License: GPL
Platform: UNKNOWN
Requires-Dist: pika
